LICENSE
README.md
gutenhaiku/__init__.py
gutenhaiku/app.py
gutenhaiku/cleaner.py
gutenhaiku/download.py
gutenhaiku/models/__init__.py
gutenhaiku/models/params
gutenhaiku/pipeline.py
gutenhaiku/utils.py
gutenhaiku-1.0.1.dist-info/entry_points.txt
gutenhaiku-1.0.1.dist-info/LICENSE
gutenhaiku-1.0.1.dist-info/WHEEL
gutenhaiku-1.0.1.dist-info/METADATA
gutenhaiku-1.0.1.dist-info/RECORD
