Metadata-Version: 2.1
Name: gutenhaiku
Version: 1.0.1
Summary: A Commandline tool to mine haiku poems from text
Home-page: https://github.com/sloev/gutenhaiku
License: MIT
Keywords: gutenhaiku,gutenberg,haiku
Author: sloev
Author-email: johannes.valbjorn@gmail.com
Requires-Python: >=3.7,<4.0
Classifier: Development Status :: 6 - Mature
Classifier: Intended Audience :: Developers
Classifier: License :: OSI Approved :: MIT License
Classifier: Natural Language :: English
Classifier: Programming Language :: Python :: 3
Classifier: Programming Language :: Python :: 3.7
Classifier: Programming Language :: Python :: 3.8
Requires-Dist: click (>=7.1.1,<8.0.0)
Requires-Dist: colorama (>=0.4.3,<0.5.0)
Requires-Dist: deepcorrect (>=1.0.5,<2.0.0)
Requires-Dist: numpy (==1.16.4)
Requires-Dist: setuptools (>=41.0.0)
Requires-Dist: silence_tensorflow (>=1.1.1,<2.0.0)
Requires-Dist: spacy (>=2.2.4,<3.0.0)
Requires-Dist: spacy_syllables (>=1.0.0,<2.0.0)
Requires-Dist: tensorboard (==1.14.0)
Requires-Dist: tensorflow (==1.14.0)
Project-URL: Repository, https://github.com/sloev/gutenhaiku
